qdk/__init__.py
qdk/estimator.py
qdk/openqasm.py
qdk/qiskit.py
qdk/qsharp.py
qdk/simulation.py
qdk/widgets.py
qdk/azure/__init__.py
qdk/azure/argument_types.py
qdk/azure/cirq.py
qdk/azure/job.py
qdk/azure/qiskit.py
qdk/azure/target/__init__.py
qdk/azure/target/rigetti.py
qdk-1.25.1.dist-info/METADATA
qdk-1.25.1.dist-info/WHEEL
qdk-1.25.1.dist-info/top_level.txt
qdk-1.25.1.dist-info/RECORD
