Metadata-Version: 2.4
Name: qdk
Version: 1.25.1
Summary: Quantum Development Kit Python Package
Author: Microsoft
Requires-Python: >=3.10
Requires-Dist: qsharp==1.25.1
Requires-Dist: pyqir<0.12
Provides-Extra: jupyter
Requires-Dist: qsharp-widgets==1.25.1; extra == "jupyter"
Requires-Dist: qsharp-jupyterlab==1.25.1; extra == "jupyter"
Provides-Extra: azure
Requires-Dist: azure-quantum>=3.5.0; extra == "azure"
Provides-Extra: qiskit
Requires-Dist: qiskit<3.0.0,>=1.2.2; extra == "qiskit"
Provides-Extra: cirq
Requires-Dist: cirq-core<=1.4.1,>=1.3.0; extra == "cirq"
Requires-Dist: cirq-ionq<=1.4.1,>=1.3.0; extra == "cirq"
Provides-Extra: all
Requires-Dist: qsharp-widgets==1.25.1; extra == "all"
Requires-Dist: azure-quantum>=3.5.0; extra == "all"
Requires-Dist: qiskit<3.0.0,>=1.2.2; extra == "all"
Requires-Dist: cirq-core<=1.4.1,>=1.3.0; extra == "all"
Requires-Dist: cirq-ionq<=1.4.1,>=1.3.0; extra == "all"
Requires-Dist: qsharp-jupyterlab==1.25.1; extra == "all"
